example_emmo00/__init__.py
example_emmo00/main.py
example_emmo00-0.0.8.dist-info/LICENSE
example_emmo00-0.0.8.dist-info/METADATA
example_emmo00-0.0.8.dist-info/WHEEL
example_emmo00-0.0.8.dist-info/top_level.txt
example_emmo00-0.0.8.dist-info/RECORD
