Metadata-Version: 2.1
Name: example_emmo00
Version: 0.0.8
Summary: example upload
Author: Nwafor Emmanuel
Author-email: test@test.com
Classifier: Programming Language :: Python :: 3
Classifier: License :: OSI Approved :: MIT License
Classifier: Operating System :: OS Independent
Requires-Python: >=3.7
License-File: LICENSE
